{
    "1": {
        "to": 1,
        "%total%": 1
    },
    "2": {
        "trillion": 1,
        "%total%": 1
    },
    "7": {
        "trillion": 1,
        "%total%": 1
    },
    "19": {
        "years,": 1,
        "%total%": 1
    },
    "232": {
        "Tariffs": 1,
        "%total%": 1
    },
    "%EOL%": {
        "232": 0.010638297872340425,
        "RT": 0.031914893617021274,
        "%total%": 94,
        "co/JE35yONsry": 0.0425531914893617,
        "co/hme0eihP9c": 0.05319148936170213,
        "Tremendous": 0.06382978723404255,
        "Look": 0.07446808510638298,
        "”": 0.11702127659574468,
        "Nice!": 0.1276595744680851,
        "He": 0.15957446808510636,
        "Deal": 0.17021276595744678,
        "co/pYoiLjM0pz": 0.19148936170212763,
        "Much": 0.20212765957446804,
        "My": 0.21276595744680846,
        "%EOL%": 0.44680851063829785,
        "but": 0.4574468085106383,
        "This": 0.48936170212765956,
        "Keep": 0.5,
        "Don't": 0.5106382978723404,
        "co/SK91xliCUQ": 0.5212765957446808,
        "Badly": 0.5319148936170212,
        "https://t": 0.5425531914893615,
        "co/aMzUz516Dn": 0.5531914893617019,
        "So": 0.5638297872340423,
        "co/eHX3Z5CMXb": 0.5744680851063827,
        "They": 0.5851063829787231,
        "It’s": 0.5957446808510635,
        "Perhaps": 0.6063829787234039,
        "co/NmaasMxOLE": 0.6170212765957442,
        "co/7tMG5NtvwO": 0.6276595744680846,
        "Now": 0.638297872340425,
        "Strong": 0.6489361702127654,
        "We": 0.691489361702127,
        "As": 0.7021276595744674,
        "co/Uc81DzHbu2": 0.7127659574468078,
        "S": 0.7234042553191482,
        "Created": 0.7340425531914886,
        "co/TtQy5yJDku": 0.744680851063829,
        "co/4DGpumMISf": 0.7553191489361694,
        "Pulitzer": 0.7659574468085097,
        "co/PjD6…": 0.7765957446808501,
        "at": 0.7872340425531905,
        "But": 0.8085106382978714,
        "No": 0.8191489361702118,
        "Lets": 0.8297872340425522,
        "The": 0.8404255319148926,
        "Thank": 0.8510638297872329,
        "co/jwsb75t0WW": 0.8617021276595733,
        "co/l5nVFKI9fr": 0.8723404255319137,
        "co/vGPOelEesM": 0.8829787234042541,
        "Tariffs": 0.8936170212765945,
        "Pittsburgh": 0.9042553191489349,
        "USA": 0.9148936170212753,
        "co/XPXjxli6uc": 0.9255319148936156,
        "co/RtSI3j1GWH": 0.936170212765956,
        "#NationalDayOfPrayer": 0.9468085106382964,
        "co/1a7zphaE6z": 0.9574468085106368,
        "and": 0.9680851063829772,
        "I’ve": 0.9787234042553176,
        "Steve": 0.9999999999999984
    },
    "RT": {
        "@anshulblp1996:": 0.043478260869565216,
        "%total%": 23,
        "@TrumpStudents:": 0.08695652173913043,
        "@charliekirk11:": 0.13043478260869565,
        "@WhiteHouse:": 0.30434782608695654,
        "@realDonaldTrump:": 0.34782608695652173,
        "@PrisonPlanet:": 0.43478260869565216,
        "@iheartmindy:": 0.4782608695652174,
        "@Lauren_Southern:": 0.5217391304347826,
        "@JeremyDBoreing:": 0.5652173913043478,
        "@SharylAttkisson:": 0.6521739130434783,
        "@EricTrump:": 0.6956521739130435,
        "@DeepStateExpose:": 0.7391304347826086,
        "@DevinNunes:": 0.7826086956521738,
        "@MariaBartiromo:": 0.8695652173913042,
        "@ByronYork:": 0.9130434782608694,
        "@kenvogel:": 0.9565217391304346,
        "@RichLowry:": 0.9999999999999998
    },
    "@anshulblp1996:": {
        "@realDonaldTrump": 1,
        "%total%": 1
    },
    "@realDonaldTrump": {
        "https://t": 0.2,
        "%total%": 5,
        "With": 0.4,
        "@FoxNews": 0.6000000000000001,
        "is": 1
    },
    "https://t": {
        "%EOL%": 1,
        "%total%": 19
    },
    "co/JE35yONsry": {
        "RT": 1,
        "%total%": 1
    },
    "@TrumpStudents:": {
        "@realDonaldTrump": 1,
        "%total%": 1
    },
    "With": {
        "President": 1,
        "%total%": 1
    },
    "President": {
        "Trump": 0.3333333333333333,
        "%total%": 6,
        "Putin": 0.6666666666666666,
        "@realDonaldTrump": 1
    },
    "Trump": {
        "leading": 0.16666666666666666,
        "%total%": 6,
        "stands": 0.3333333333333333,
        "was": 0.5,
        "welcomed": 0.6666666666666666,
        "Campaign": 0.8333333333333333,
        "obstruction": 0.9999999999999999
    },
    "leading": {
        "us,": 1,
        "%total%": 1
    },
    "us,": {
        "America": 1,
        "%total%": 1
    },
    "America": {
        "is": 0.5,
        "%total%": 4,
        "must": 0.75,
        "—": 1
    },
    "is": {
        "a": 0.09090909090909091,
        "%total%": 22,
        "possible,": 0.13636363636363635,
        "about": 0.18181818181818182,
        "@nytimes,": 0.2272727272727273,
        "FAKE": 0.27272727272727276,
        "truly": 0.31818181818181823,
        "nothing": 0.3636363636363637,
        "nonsense": 0.40909090909090917,
        "very": 0.45454545454545464,
        "the": 0.5454545454545455,
        "rebelling": 0.5909090909090909,
        "running": 0.6363636363636364,
        "now": 0.6818181818181818,
        "yet": 0.7272727272727272,
        "getting": 0.7727272727272726,
        "bigger": 0.818181818181818,
        "fixing": 0.8636363636363634,
        "making": 0.9090909090909088,
        "again": 0.9545454545454543,
        "BOOMING!": 0.9999999999999997
    },
    "a": {
        "BETTER": 0.0625,
        "%total%": 16,
        "good/great": 0.125,
        "better": 0.1875,
        "handful": 0.25,
        "private": 0.3125,
        "USA": 0.375,
        "bipartisan": 0.4375,
        "complete": 0.5,
        "fantastic": 0.5625,
        "long": 0.625,
        "good": 0.6875,
        "bad": 0.75,
        "great": 0.8125,
        "truly": 0.875,
        "Ukrainian": 0.9375,
        "prosecutor": 1
    },
    "BETTER": {
        "and": 1,
        "%total%": 1
    },
    "and": {
        "SAFER": 0.03125,
        "%total%": 32,
        "see": 0.0625,
        "safer": 0.09375,
        "property!": 0.125,
        "ready": 0.15625,
        "the": 0.25,
        "Paul": 0.28125,
        "Silk": 0.3125,
        "what": 0.34375,
        "we’re": 0.375,
        "worse": 0.40625,
        "we": 0.4375,
        "watching,": 0.46875,
        "has": 0.5,
        "Total": 0.53125,
        "Healthcare": 0.5625,
        "even": 0.59375,
        "very": 0.625,
        "everyone": 0.65625,
        "manufacturing": 0.6875,
        "President": 0.71875,
        "Democrats": 0.75,
        "do": 0.78125,
        "each": 0.8125,
        "USA": 0.84375,
        "Aluminum": 0.875,
        "ensure": 0.90625,
        "worship": 0.9375,
        "deregulation": 0.96875,
        "a": 1
    },
    "SAFER": {
        "place🇺🇸": 1,
        "%total%": 1
    },
    "place🇺🇸": {
        "RT": 1,
        "%total%": 1
    },
    "@charliekirk11:": {
        "BOOM:": 1,
        "%total%": 1
    },
    "BOOM:": {
        "Despite": 1,
        "%total%": 1
    },
    "Despite": {
        "horrendous": 1,
        "%total%": 1
    },
    "horrendous": {
        "media": 1,
        "%total%": 1
    },
    "media": {
        "treatment": 0.5,
        "%total%": 2,
        "platforms": 1
    },
    "treatment": {
        "coverage": 1,
        "%total%": 1
    },
    "coverage": {
        "Trump": 1,
        "%total%": 1
    },
    "stands": {
        "at": 1,
        "%total%": 1
    },
    "at": {
        "51%": 0.2,
        "%total%": 5,
        "establishment": 0.4,
        "@TrumpGolfPhilly!": 0.6000000000000001,
        "a": 0.8,
        "every": 1
    },
    "51%": {
        "approval": 1,
        "%total%": 1
    },
    "approval": {
        "rating!": 1,
        "%total%": 1
    },
    "rating!": {
        "They": 1,
        "%total%": 1
    },
    "They": {
        "tried": 0.5,
        "%total%": 2,
        "work": 1
    },
    "tried": {
        "to": 1,
        "%total%": 1
    },
    "to": {
        "2": 0.02702702702702703,
        "defame": 0.05405405405405406,
        "%total%": 37,
        "interfere": 0.08108108108108109,
        "break": 0.10810810810810811,
        "me": 0.16216216216216217,
        "watch": 0.21621621621621623,
        "happen!": 0.24324324324324326,
        "be": 0.2702702702702703,
        "decide": 0.2972972972972973,
        "censor/": 0.32432432432432434,
        "some": 0.35135135135135137,
        "Islam": 0.3783783783783784,
        "know": 0.40540540540540543,
        "with": 0.43243243243243246,
        "@seanhannity": 0.4594594594594595,
        "confront": 0.4864864864864865,
        "help!": 0.5135135135135136,
        "see": 0.5405405405405406,
        "them": 0.5675675675675675,
        "monitor": 0.5945945945945945,
        "come!": 0.6216216216216215,
        "Lowest": 0.6486486486486485,
        "the": 0.6756756756756754,
        "avoid": 0.7027027027027024,
        "spy": 0.7297297297297294,
        "bring": 0.7567567567567564,
        "gain": 0.7837837837837833,
        "make": 0.8108108108108103,
        "get": 0.8378378378378373,
        "business": 0.8648648648648642,
        "@U_S_Steel": 0.8918918918918912,
        "protect": 0.9189189189189182,
        "work": 0.9459459459459452,
        "withdraw": 0.9729729729729721,
        "fire": 0.9999999999999991
    },
    "defame": {
        "him": 1,
        "%total%": 1
    },
    "him": {
        "They…": 0.3333333333333333,
        "%total%": 3,
        "&amp;": 0.6666666666666666,
        "out": 1
    },
    "They…": {
        "RT": 1,
        "%total%": 1
    },
    "@WhiteHouse:": {
        "We're": 0.25,
        "%total%": 4,
        "President": 0.75,
        "Happy": 1
    },
    "We're": {
        "killing": 1,
        "%total%": 1
    },
    "killing": {
        "it": 1,
        "%total%": 1
    },
    "it": {
        "on": 0.3333333333333333,
        "%total%": 3,
        "%EOL%": 0.6666666666666666,
        "now!": 1
    },
    "on": {
        "the": 0.08333333333333333,
        "%total%": 12,
        "“Russia": 0.16666666666666666,
        "Twitter": 0.25,
        "social": 0.41666666666666663,
        "their": 0.49999999999999994,
        "Crime,": 0.5833333333333333,
        "front": 0.6666666666666666,
        "Trump": 0.8333333333333333,
        "Days": 0.9166666666666666,
        "this": 1
    },
    "the": {
        "economy!": 0.02040816326530612,
        "%total%": 49,
        "Fake": 0.04081632653061224,
        "great": 0.08163265306122448,
        "Radical": 0.1020408163265306,
        "Russia": 0.12244897959183672,
        "power": 0.14285714285714285,
        "racist": 0.16326530612244897,
        "new": 0.18367346938775508,
        "platfo…": 0.2040816326530612,
        "distasteful,": 0.22448979591836732,
        "door": 0.24489795918367344,
        "pressure": 0.26530612244897955,
        "team": 0.2857142857142857,
        "Middle": 0.30612244897959184,
        "last": 0.326530612244898,
        "best": 0.38775510204081637,
        "Russians": 0.4081632653061225,
        "devastating": 0.42857142857142866,
        "local": 0.4489795918367348,
        "impacts": 0.46938775510204095,
        "destructive": 0.4897959183673471,
        "censorship": 0.5102040816326532,
        "United": 0.5306122448979593,
        "Slovak": 0.5510204081632655,
        "Oval": 0.5714285714285716,
        "Great": 0.5918367346938778,
        "Republican": 0.6122448979591839,
        "“Russian": 0.63265306122449,
        "Witch": 0.6530612244897962,
        "ENVY": 0.6734693877551023,
        "WORLD": 0.6938775510204085,
        "lowest": 0.7142857142857146,
        "reverse!": 0.7346938775510208,
        "good": 0.7551020408163269,
        "American": 0.7755102040816331,
        "other": 0.7959183673469392,
        "Holocaust:": 0.8163265306122454,
        "hands": 0.8367346938775515,
        "Goodness": 0.8571428571428577,
        "Grace": 0.8775510204081638,
        "eternal": 0.8979591836734699,
        "Fed": 0.9183673469387761,
        "battle": 0.9387755102040822,
        "talk": 0.9591836734693884,
        "first": 0.9795918367346945,
        "last,": 1.0000000000000007
    },
    "economy!": {
        "🔥": 1,
        "%total%": 1
    },
    "🔥": {
        "https://t": 1,
        "%total%": 1
    },
    "co/hme0eihP9c": {
        "Very": 1,
        "%total%": 1
    },
    "Very": {
        "good": 0.5,
        "%total%": 2,
        "productive": 1
    },
    "good": {
        "call": 0.25,
        "%total%": 4,
        "conversation": 0.5,
        "thing,": 0.75,
        "of": 1
    },
    "call": {
        "yesterday": 1,
        "%total%": 1
    },
    "yesterday": {
        "with": 1,
        "%total%": 1
    },
    "with": {
        "President": 0.2,
        "%total%": 10,
        "Russia,": 0.4,
        "him": 0.5,
        "the": 0.7,
        "@IAGovernor,": 0.7999999999999999,
        "Russia": 0.8999999999999999,
        "me": 0.9999999999999999
    },
    "Putin": {
        "of": 1,
        "%total%": 2
    },
    "of": {
        "1": 0.030303030303030304,
        "Russia": 0.09090909090909091,
        "%total%": 33,
        "North": 0.12121212121212122,
        "what": 0.15151515151515152,
        "giant": 0.18181818181818182,
        "God,": 0.21212121212121213,
        "#TomFazios": 0.24242424242424243,
        "all": 0.2727272727272727,
        "course": 0.303030303030303,
        "IA,": 0.33333333333333326,
        "the": 0.5151515151515151,
        "AMERICAN": 0.5454545454545454,
        "America": 0.5757575757575757,
        "Firefighters": 0.606060606060606,
        "office": 0.6363636363636362,
        "Pennsylvania": 0.6666666666666665,
        "hard": 0.6969696969696968,
        "Remembrance": 0.7272727272727271,
        "Victims": 0.7575757575757573,
        "prayer,": 0.8181818181818179,
        "our": 0.8787878787878785,
        "liberty,": 0.9090909090909087,
        "faith": 0.939393939393939,
        "ideas": 0.9696969696969693,
        "judgme…": 0.9999999999999996
    },
    "Russia": {
        "%EOL%": 0.5,
        "%total%": 4,
        "Collusion": 0.75,
        "(of": 1
    },
    "Tremendous": {
        "potential": 1,
        "%total%": 1
    },
    "potential": {
        "for": 0.5,
        "%total%": 2,
        "of": 1
    },
    "for": {
        "a": 0.06666666666666667,
        "%total%": 15,
        "knowingly": 0.13333333333333333,
        "quoting": 0.2,
        "any": 0.26666666666666666,
        "g…": 0.3333333333333333,
        "me": 0.39999999999999997,
        "you": 0.4666666666666666,
        "Conservatives": 0.5333333333333333,
        "his": 0.6,
        "Congress,": 0.6666666666666666,
        "the": 0.7999999999999999,
        "investing": 0.8666666666666666,
        "this": 0.9333333333333332,
        "all": 0.9999999999999999
    },
    "good/great": {
        "relationship": 1,
        "%total%": 1
    },
    "relationship": {
        "with": 1,
        "%total%": 1
    },
    "Russia,": {
        "despite": 0.5,
        "%total%": 2,
        "China,": 1
    },
    "despite": {
        "what": 1,
        "%total%": 1
    },
    "what": {
        "you": 0.25,
        "%total%": 4,
        "they": 0.5,
        "Trump": 0.75,
        "has": 1
    },
    "you": {
        "read": 0.3333333333333333,
        "%total%": 3,
        "on": 0.6666666666666666,
        "and": 1
    },
    "read": {
        "and": 1,
        "%total%": 1
    },
    "see": {
        "in": 0.5,
        "%total%": 2,
        "Conservative": 1
    },
    "in": {
        "the": 0.2857142857142857,
        "%total%": 14,
        "this": 0.3571428571428571,
        "close": 0.4285714285714285,
        "April,": 0.5714285714285714,
        "space,": 0.6428571428571428,
        "attempts": 0.7142857142857142,
        "fact,": 0.7857142857142856,
        "America's": 0.857142857142857,
        "our": 0.9285714285714284,
        "a": 0.9999999999999998
    },
    "Fake": {
        "News": 1,
        "%total%": 1
    },
    "News": {
        "Media": 1,
        "%total%": 1
    },
    "Media": {
        "%EOL%": 0.3333333333333333,
        "%total%": 3,
        "apologize": 0.6666666666666666,
        "is": 1
    },
    "Look": {
        "how": 1,
        "%total%": 1
    },
    "how": {
        "they": 1,
        "%total%": 1
    },
    "they": {
        "have": 0.16666666666666666,
        "%total%": 6,
        "do": 0.3333333333333333,
        "won’t": 0.5,
        "are": 0.6666666666666666,
        "will": 0.8333333333333333,
        "were": 0.9999999999999999
    },
    "have": {
        "misled": 0.2,
        "%total%": 5,
        "been": 0.4,
        "what’s": 0.6000000000000001,
        "always": 0.8,
        "produced": 1
    },
    "misled": {
        "you": 1,
        "%total%": 1
    },
    "“Russia": {
        "Collusion": 1,
        "%total%": 1
    },
    "Collusion": {
        "%EOL%": 0.3333333333333333,
        "%total%": 3,
        "Delusion": 0.6666666666666666,
        "with": 1
    },
    "”": {
        "The": 0.25,
        "%total%": 4,
        "George": 0.5,
        "Very": 0.75,
        "@foxandfriends": 1
    },
    "The": {
        "World": 0.1,
        "%total%": 10,
        "real": 0.2,
        "support": 0.30000000000000004,
        "'elite'": 0.4,
        "wonderful": 0.5,
        "International": 0.6,
        "New": 0.7,
        "Mueller": 0.7999999999999999,
        "Steel": 0.8999999999999999,
        "BIDENS": 0.9999999999999999
    },
    "World": {
        "can": 1,
        "%total%": 1
    },
    "can": {
        "be": 0.25,
        "%total%": 4,
        "ban": 0.5,
        "all": 0.75,
        "live,": 1
    },
    "be": {
        "a": 0.2,
        "%total%": 5,
        "on": 0.4,
        "labeled": 0.6000000000000001,
        "trus…": 0.8,
        "strengthened": 1
    },
    "better": {
        "and": 1,
        "%total%": 1
    },
    "safer": {
        "place": 1,
        "%total%": 1
    },
    "place": {
        "%EOL%": 0.5,
        "%total%": 2,
        "our": 1
    },
    "Nice!": {
        "Anything": 1,
        "%total%": 1
    },
    "Anything": {
        "in": 1,
        "%total%": 1
    },
    "this": {
        "very": 0.25,
        "%total%": 4,
        "day": 0.75,
        "wondrous": 1
    },
    "very": {
        "interesting": 0.25,
        "%total%": 4,
        "sad": 0.5,
        "foolish": 0.75,
        "good": 1
    },
    "interesting": {
        "world": 1,
        "%total%": 1
    },
    "world": {
        "is": 1,
        "%total%": 1
    },
    "possible,": {
        "but": 0.5,
        "%total%": 2,
        "it’s": 1
    },
    "but": {
        "I": 0.5,
        "%total%": 4,
        "@TalbertSwan": 0.75,
        "the": 1
    },
    "I": {
        "believe": 0.16666666666666666,
        "%total%": 6,
        "am": 0.6666666666666666,
        "have": 0.8333333333333333,
        "understand": 0.9999999999999999
    },
    "believe": {
        "that": 1,
        "%total%": 1
    },
    "that": {
        "Kim": 0.125,
        "%total%": 8,
        "I": 0.25,
        "it's": 0.375,
        "free": 0.5,
        "AMERICA": 0.625,
        "there": 0.75,
        "THIS": 0.875,
        "ALL": 1
    },
    "Kim": {
        "Jong": 1,
        "%total%": 1
    },
    "Jong": {
        "Un": 1,
        "%total%": 1
    },
    "Un": {
        "fully": 1,
        "%total%": 1
    },
    "fully": {
        "realizes": 1,
        "%total%": 1
    },
    "realizes": {
        "the": 1,
        "%total%": 1
    },
    "great": {
        "economic": 0.16666666666666666,
        "%total%": 6,
        "to": 0.5,
        "Country": 0.6666666666666666,
        "people": 0.8333333333333333,
        "pro-growth": 0.9999999999999999
    },
    "economic": {
        "potential": 0.5,
        "%total%": 2,
        "growth": 1
    },
    "North": {
        "Korea,": 1,
        "%total%": 2
    },
    "Korea,": {
        "&amp;": 0.5,
        "%total%": 2,
        "Nuclear": 1
    },
    "&amp;": {
        "will": 0.1,
        "%total%": 10,
        "does": 0.2,
        "Facebook": 0.30000000000000004,
        "3d": 0.4,
        "MO": 0.5,
        "bigger": 0.6,
        "time": 0.7,
        "much": 0.7999999999999999,
        "we": 0.8999999999999999,
        "the": 0.9999999999999999
    },
    "will": {
        "do": 0.25,
        "%total%": 8,
        "happen!": 0.375,
        "the": 0.5,
        "vote": 0.625,
        "declassify": 0.75,
        "become": 0.875,
        "forever": 1
    },
    "do": {
        "nothing": 0.16666666666666666,
        "%total%": 6,
        "is": 0.3333333333333333,
        "not": 0.5,
        "a": 0.6666666666666666,
        "Immigration": 0.8333333333333333,
        "it": 0.9999999999999999
    },
    "nothing": {
        "to": 0.5,
        "%total%": 2,
        "easy": 1
    },
    "interfere": {
        "or": 1,
        "%total%": 1
    },
    "or": {
        "end": 0.3333333333333333,
        "%total%": 3,
        "else!!!": 0.6666666666666666,
        "we": 1
    },
    "end": {
        "it": 1,
        "%total%": 1
    },
    "He": {
        "also": 0.3333333333333333,
        "%total%": 3,
        "doesn’t": 0.6666666666666666,
        "will": 1
    },
    "also": {
        "knows": 1,
        "%total%": 1
    },
    "knows": {
        "that": 1,
        "%total%": 1
    },
    "am": {
        "with": 0.3333333333333333,
        "%total%": 3,
        "looking": 0.6666666666666666,
        "continuing": 1
    },
    "does": {
        "not": 1,
        "%total%": 1
    },
    "not": {
        "want": 0.25,
        "%total%": 4,
        "understand": 0.5,
        "a": 0.75,
        "deciding": 1
    },
    "want": {
        "to": 1,
        "%total%": 1
    },
    "break": {
        "his": 1,
        "%total%": 1
    },
    "his": {
        "promise": 0.5,
        "%total%": 2,
        "first": 1
    },
    "promise": {
        "to": 1,
        "%total%": 1
    },
    "me": {
        "%EOL%": 0.25,
        "%total%": 4,
        "for": 0.5,
        "has": 0.75,
        "toward": 1
    },
    "Deal": {
        "will": 1,
        "%total%": 1
    },
    "happen!": {
        "RT": 0.5,
        "%total%": 2,
        "Why": 1
    },
    "@realDonaldTrump:": {
        "So": 1,
        "%total%": 1
    },
    "So": {
        "great": 0.5,
        "%total%": 4,
        "James": 0.75,
        "surprised": 1
    },
    "watch": {
        "this!": 1,
        "%total%": 2
    },
    "this!": {
        "https://t": 1,
        "%total%": 2
    },
    "co/pYoiLjM0pz": {
        "When": 0.5,
        "%total%": 2,
        "There": 1
    },
    "When": {
        "will": 0.3333333333333333,
        "%total%": 3,
        "did": 1
    },
    "Radical": {
        "Left": 1,
        "%total%": 1
    },
    "Left": {
        "Wing": 1,
        "%total%": 1
    },
    "Wing": {
        "Media": 1,
        "%total%": 1
    },
    "apologize": {
        "to": 1,
        "%total%": 1
    },
    "knowingly": {
        "getting": 1,
        "%total%": 1
    },
    "getting": {
        "the": 0.25,
        "%total%": 4,
        "worse": 0.5,
        "along": 0.75,
        "involved": 1
    },
    "Delusion": {
        "story": 1,
        "%total%": 1
    },
    "story": {
        "so": 0.3333333333333333,
        "%total%": 3,
        "is": 0.6666666666666666,
        "going": 1
    },
    "so": {
        "wrong?": 0.25,
        "%total%": 4,
        "horribly": 0.5,
        "hard": 0.75,
        "after": 1
    },
    "wrong?": {
        "The": 1,
        "%total%": 1
    },
    "real": {
        "story": 1,
        "%total%": 1
    },
    "about": {
        "to": 0.3333333333333333,
        "%total%": 3,
        "a": 0.6666666666666666,
        "Mueller": 1
    },
    "Why": {
        "is": 1,
        "%total%": 1
    },
    "@nytimes,": {
        "@washingtonpost,": 1,
        "%total%": 1
    },
    "@washingtonpost,": {
        "@CNN,": 1,
        "%total%": 1
    },
    "@CNN,": {
        "@MSNBC": 1,
        "%total%": 1
    },
    "@MSNBC": {
        "allowed": 1,
        "%total%": 1
    },
    "allowed": {
        "to": 1,
        "%total%": 1
    },
    "Twitter": {
        "&amp;": 0.5,
        "%total%": 2,
        "for": 1
    },
    "Facebook": {
        "%EOL%": 0.6666666666666666,
        "%total%": 3,
        "can": 1
    },
    "Much": {
        "of": 1,
        "%total%": 1
    },
    "FAKE": {
        "NEWS!": 1,
        "%total%": 1
    },
    "NEWS!": {
        "RT": 1,
        "%total%": 1
    },
    "@PrisonPlanet:": {
        "“Dangerous”": 0.5,
        "%total%": 2,
        "The": 1
    },
    "“Dangerous”": {
        "%EOL%": 1,
        "%total%": 1
    },
    "My": {
        "opinions?": 0.5,
        "%total%": 2,
        "team": 1
    },
    "opinions?": {
        "Or": 1,
        "%total%": 1
    },
    "Or": {
        "giving": 1,
        "%total%": 1
    },
    "giving": {
        "a": 1,
        "%total%": 1
    },
    "handful": {
        "of": 1,
        "%total%": 1
    },
    "giant": {
        "partisan": 1,
        "%total%": 1
    },
    "partisan": {
        "corporations": 1,
        "%total%": 1
    },
    "corporations": {
        "the": 1,
        "%total%": 1
    },
    "power": {
        "to": 1,
        "%total%": 1
    },
    "decide": {
        "who": 1,
        "%total%": 1
    },
    "who": {
        "has": 0.5,
        "%total%": 2,
        "think": 1
    },
    "has": {
        "free": 0.14285714285714285,
        "%total%": 7,
        "been": 0.5714285714285714,
        "spent": 0.7142857142857142,
        "my": 0.857142857142857,
        "decided": 0.9999999999999998
    },
    "free": {
        "speech?…": 0.5,
        "%total%": 2,
        "speech": 1
    },
    "speech?…": {
        "RT": 1,
        "%total%": 1
    },
    "@iheartmindy:": {
        "So": 1,
        "%total%": 1
    },
    "James": {
        "Woods": 1,
        "%total%": 2
    },
    "Woods": {
        "was": 0.5,
        "%total%": 2,
        "banned": 1
    },
    "was": {
        "kicked": 0.25,
        "%total%": 4,
        "up": 0.5,
        "a": 0.75,
        "No": 1
    },
    "kicked": {
        "off": 1,
        "%total%": 1
    },
    "off": {
        "Twitter": 1,
        "%total%": 1
    },
    "quoting": {
        "Ralph": 1,
        "%total%": 1
    },
    "Ralph": {
        "Waldo": 1,
        "%total%": 1
    },
    "Waldo": {
        "Emerson": 1,
        "%total%": 1
    },
    "Emerson": {
        "%EOL%": 1,
        "%total%": 1
    },
    "@TalbertSwan": {
        "the": 1,
        "%total%": 1
    },
    "racist": {
        "fake": 1,
        "%total%": 1
    },
    "fake": {
        "man": 1,
        "%total%": 1
    },
    "man": {
        "of": 1,
        "%total%": 1
    },
    "God,": {
        "that’…": 1,
        "%total%": 1
    },
    "that’…": {
        "RT": 1,
        "%total%": 1
    },
    "@Lauren_Southern:": {
        "Lmao": 1,
        "%total%": 1
    },
    "Lmao": {
        "at": 1,
        "%total%": 1
    },
    "establishment": {
        "conservatives": 1,
        "%total%": 1
    },
    "conservatives": {
        "who": 1,
        "%total%": 1
    },
    "think": {
        "they": 1,
        "%total%": 1
    },
    "won’t": {
        "be": 1,
        "%total%": 1
    },
    "labeled": {
        "the": 1,
        "%total%": 1
    },
    "new": {
        "“dangerous”": 1,
        "%total%": 1
    },
    "“dangerous”": {
        "/": 1,
        "%total%": 1
    },
    "/": {
        "“extremist”": 1,
        "%total%": 1
    },
    "“extremist”": {
        "voices": 1,
        "%total%": 1
    },
    "voices": {
        "when": 1,
        "%total%": 1
    },
    "when": {
        "thos…": 0.5,
        "%total%": 2,
        "our": 1
    },
    "thos…": {
        "RT": 1,
        "%total%": 1
    },
    "@JeremyDBoreing:": {
        "Those": 1,
        "%total%": 1
    },
    "Those": {
        "suggesting": 1,
        "%total%": 1
    },
    "suggesting": {
        "Facebook": 1,
        "%total%": 1
    },
    "ban": {
        "anyone": 1,
        "%total%": 1
    },
    "anyone": {
        "for": 1,
        "%total%": 1
    },
    "any": {
        "reason": 1,
        "%total%": 1
    },
    "reason": {
        "because": 1,
        "%total%": 1
    },
    "because": {
        "they": 1,
        "%total%": 1
    },
    "are": {
        "a": 0.14285714285714285,
        "%total%": 7,
        "here": 0.2857142857142857,
        "monitoring": 0.42857142857142855,
        "the": 0.5714285714285714,
        "working": 0.7142857142857142,
        "entangled": 0.857142857142857,
        "demonstrating": 0.9999999999999998
    },
    "private": {
        "company": 1,
        "%total%": 1
    },
    "company": {
        "do": 1,
        "%total%": 1
    },
    "understand": {
        "the": 1,
        "%total%": 2
    },
    "platfo…": {
        "RT": 1,
        "%total%": 1
    },
    "@SharylAttkisson:": {
        "When": 1,
        "%total%": 2
    },
    "did": {
        "we": 0.6666666666666666,
        "%total%": 3,
        "decide,": 1
    },
    "we": {
        "decide,": 0.09090909090909091,
        "%total%": 11,
        "cannot": 0.18181818181818182,
        "quit": 0.2727272727272727,
        "open": 0.36363636363636365,
        "are": 0.4545454545454546,
        "have": 0.5454545454545455,
        "once": 0.6363636363636365,
        "pray": 0.7272727272727274,
        "unite": 0.8181818181818183,
        "renew": 0.9090909090909093,
        "expect,": 1.0000000000000002
    },
    "decide,": {
        "as": 0.5,
        "%total%": 2,
        "didn't": 1
    },
    "as": {
        "Americans,": 0.16666666666666666,
        "%total%": 6,
        "FREEDOM": 0.3333333333333333,
        "the": 0.5,
        "bad": 0.6666666666666666,
        "possible,": 0.8333333333333333,
        "corrup…": 0.9999999999999999
    },
    "Americans,": {
        "that": 1,
        "%total%": 1
    },
    "it's": {
        "ok": 1,
        "%total%": 1
    },
    "ok": {
        "fo": 1,
        "%total%": 1
    },
    "fo": {
        "govt": 1,
        "%total%": 1
    },
    "govt": {
        "&amp;": 1,
        "%total%": 1
    },
    "3d": {
        "parties": 1,
        "%total%": 1
    },
    "parties": {
        "to": 1,
        "%total%": 1
    },
    "censor/": {
        "curate": 1,
        "%total%": 1
    },
    "curate": {
        "our": 1,
        "%total%": 1
    },
    "our": {
        "info?": 0.125,
        "%total%": 8,
        "great": 0.25,
        "steel": 0.375,
        "hopes": 0.5,
        "Creator": 0.625,
        "resolve": 0.75,
        "people": 0.875,
        "Country": 1
    },
    "info?": {
        "That": 1,
        "%total%": 1
    },
    "That": {
        "we": 1,
        "%total%": 1
    },
    "cannot": {
        "be": 1,
        "%total%": 1
    },
    "trus…": {
        "RT": 1,
        "%total%": 1
    },
    "quit": {
        "teaching/understanding": 1,
        "%total%": 1
    },
    "teaching/understanding": {
        "that": 1,
        "%total%": 1
    },
    "speech": {
        "means": 1,
        "%total%": 1
    },
    "means": {
        "protecting": 1,
        "%total%": 1
    },
    "protecting": {
        "the": 1,
        "%total%": 1
    },
    "distasteful,": {
        "lest": 1,
        "%total%": 1
    },
    "lest": {
        "we": 1,
        "%total%": 1
    },
    "open": {
        "the": 1,
        "%total%": 1
    },
    "door": {
        "for": 1,
        "%total%": 1
    },
    "g…": {
        "RT": 1,
        "%total%": 1
    },
    "support": {
        "for": 1,
        "%total%": 1
    },
    "been": {
        "incredible": 0.25,
        "%total%": 4,
        "treated": 0.5,
        "done": 0.75,
        "an": 1
    },
    "incredible": {
        "%EOL%": 1,
        "%total%": 1
    },
    "This": {
        "could": 0.16666666666666666,
        "%total%": 6,
        "is": 0.6666666666666666,
        "whole": 0.8333333333333333,
        "will": 0.9999999999999999
    },
    "could": {
        "actually": 1,
        "%total%": 1
    },
    "actually": {
        "lead": 1,
        "%total%": 1
    },
    "lead": {
        "to": 1,
        "%total%": 1
    },
    "some": {
        "genuine": 1,
        "%total%": 1
    },
    "genuine": {
        "change": 1,
        "%total%": 1
    },
    "change": {
        "%EOL%": 1,
        "%total%": 1
    },
    "Keep": {
        "up": 1,
        "%total%": 1
    },
    "up": {
        "the": 0.5,
        "%total%": 2,
        "to": 1
    },
    "pressure": {
        "%EOL%": 1,
        "%total%": 1
    },
    "Don't": {
        "let…": 1,
        "%total%": 1
    },
    "let…": {
        "RT": 1,
        "%total%": 1
    },
    "@EricTrump:": {
        "Great": 1,
        "%total%": 1
    },
    "Great": {
        "being": 0.5,
        "%total%": 2,
        "State": 1
    },
    "being": {
        "with": 1,
        "%total%": 1
    },
    "team": {
        "at": 0.5,
        "%total%": 2,
        "remains": 1
    },
    "@TrumpGolfPhilly!": {
        "Such": 1,
        "%total%": 1
    },
    "Such": {
        "an": 1,
        "%total%": 1
    },
    "an": {
        "unbelievable": 0.25,
        "%total%": 4,
        "astounding": 0.5,
        "outstanding": 0.75,
        "imp": 1
    },
    "unbelievable": {
        "course": 1,
        "%total%": 1
    },
    "course": {
        "and": 0.5,
        "%total%": 2,
        "is": 1
    },
    "property!": {
        "This": 1,
        "%total%": 1
    },
    "truly": {
        "one": 0.5,
        "%total%": 2,
        "fine": 1
    },
    "one": {
        "of": 1,
        "%total%": 1
    },
    "#TomFazios": {
        "gre…": 1,
        "%total%": 1
    },
    "gre…": {
        "RT": 1,
        "%total%": 1
    },
    "@DeepStateExpose:": {
        "Retweet:": 1,
        "%total%": 1
    },
    "Retweet:": {
        "The": 1,
        "%total%": 1
    },
    "'elite'": {
        "proclaim": 1,
        "%total%": 1
    },
    "proclaim": {
        "America": 1,
        "%total%": 1
    },
    "must": {
        "submit": 0.5,
        "%total%": 2,
        "come": 1
    },
    "submit": {
        "to": 1,
        "%total%": 1
    },
    "Islam": {
        "or": 1,
        "%total%": 1
    },
    "else!!!": {
        "#Trump2020": 1,
        "%total%": 1
    },
    "#Trump2020": {
        "https://t": 1,
        "%total%": 1
    },
    "co/SK91xliCUQ": {
        "So": 1,
        "%total%": 1
    },
    "There": {
        "is": 1,
        "%total%": 1
    },
    "easy": {
        "about": 1,
        "%total%": 1
    },
    "USA": {
        "Infrastructure": 0.3333333333333333,
        "%total%": 3,
        "more": 0.6666666666666666,
        "Economy": 1
    },
    "Infrastructure": {
        "Plan,": 1,
        "%total%": 1
    },
    "Plan,": {
        "especially": 1,
        "%total%": 1
    },
    "especially": {
        "when": 1,
        "%total%": 1
    },
    "Country": {
        "has": 0.5,
        "%total%": 2,
        "%EOL%": 1
    },
    "spent": {
        "an": 1,
        "%total%": 1
    },
    "astounding": {
        "7": 1,
        "%total%": 1
    },
    "trillion": {
        "dollars": 1,
        "%total%": 2
    },
    "dollars": {
        "in": 0.5,
        "%total%": 2,
        "%EOL%": 1
    },
    "Middle": {
        "East": 1,
        "%total%": 1
    },
    "East": {
        "over": 1,
        "%total%": 1
    },
    "over": {
        "the": 1,
        "%total%": 1
    },
    "last": {
        "19": 1,
        "%total%": 1
    },
    "years,": {
        "but": 1,
        "%total%": 1
    },
    "looking": {
        "hard": 0.5,
        "%total%": 2,
        "into": 1
    },
    "hard": {
        "at": 0.3333333333333333,
        "%total%": 3,
        "and": 0.6666666666666666,
        "work": 1
    },
    "bipartisan": {
        "plan": 1,
        "%total%": 1
    },
    "plan": {
        "of": 1,
        "%total%": 1
    },
    "Badly": {
        "needed!": 1,
        "%total%": 1
    },
    "needed!": {
        "RT": 1,
        "%total%": 1
    },
    "@DevinNunes:": {
        "Perhaps": 1,
        "%total%": 1
    },
    "Perhaps": {
        "the": 0.5,
        "%total%": 2,
        "they": 1
    },
    "best": {
        "@ChuckGrassley": 0.25,
        "%total%": 4,
        "is": 0.5,
        "in": 0.75,
        "to": 1
    },
    "@ChuckGrassley": {
        "clip": 1,
        "%total%": 1
    },
    "clip": {
        "of": 1,
        "%total%": 1
    },
    "all": {
        "time": 0.3333333333333333,
        "%total%": 3,
        "agree": 0.6666666666666666,
        "Americans": 1
    },
    "time": {
        "%EOL%": 0.3333333333333333,
        "%total%": 3,
        "consuming": 0.6666666666666666,
        "to": 1
    },
    "co/aMzUz516Dn": {
        "“They": 1,
        "%total%": 1
    },
    "“They": {
        "wanted": 1,
        "%total%": 1
    },
    "wanted": {
        "to": 1,
        "%total%": 1
    },
    "know": {
        "what": 0.5,
        "%total%": 2,
        "we": 1
    },
    "Russians": {
        "-": 1,
        "%total%": 1
    },
    "-": {
        "which": 0.2,
        "%total%": 5,
        "and": 0.6000000000000001,
        "too": 0.8,
        "@POTUS": 1
    },
    "which": {
        "of": 0.5,
        "%total%": 2,
        "have": 1
    },
    "nonsense": {
        "%EOL%": 1,
        "%total%": 1
    },
    "whole": {
        "thing": 1,
        "%total%": 1
    },
    "thing": {
        "was": 0.5,
        "%total%": 2,
        "%EOL%": 1
    },
    "complete": {
        "setup": 1,
        "%total%": 1
    },
    "setup": {
        "%EOL%": 1,
        "%total%": 1
    },
    "George": {
        "Papadopoulos": 1,
        "%total%": 1
    },
    "Papadopoulos": {
        "to": 1,
        "%total%": 1
    },
    "@seanhannity": {
        "As": 1,
        "%total%": 1
    },
    "As": {
        "the": 0.3333333333333333,
        "%total%": 3,
        "I": 0.6666666666666666,
        "we": 1
    },
    "people": {
        "of": 0.3333333333333333,
        "%total%": 3,
        "%EOL%": 0.6666666666666666,
        "can": 1
    },
    "IA,": {
        "IL,": 1,
        "%total%": 1
    },
    "IL,": {
        "&amp;": 1,
        "%total%": 1
    },
    "MO": {
        "continue": 1,
        "%total%": 1
    },
    "continue": {
        "to": 1,
        "%total%": 1
    },
    "confront": {
        "the": 1,
        "%total%": 1
    },
    "devastating": {
        "flooding,": 1,
        "%total%": 1
    },
    "flooding,": {
        "know": 1,
        "%total%": 1
    },
    "here": {
        "for": 1,
        "%total%": 1
    },
    "ready": {
        "to": 1,
        "%total%": 1
    },
    "help!": {
        "My": 1,
        "%total%": 1
    },
    "remains": {
        "in": 1,
        "%total%": 1
    },
    "close": {
        "contact": 1,
        "%total%": 1
    },
    "contact": {
        "with": 1,
        "%total%": 1
    },
    "@IAGovernor,": {
        "@GovParsonMO,": 1,
        "%total%": 1
    },
    "@GovParsonMO,": {
        "@GovPritzker,": 1,
        "%total%": 1
    },
    "@GovPritzker,": {
        "and": 1,
        "%total%": 1
    },
    "local": {
        "officials": 1,
        "%total%": 1
    },
    "officials": {
        "managing": 1,
        "%total%": 1
    },
    "managing": {
        "the": 1,
        "%total%": 1
    },
    "impacts": {
        "of": 1,
        "%total%": 1
    },
    "destructive": {
        "flooding": 1,
        "%total%": 1
    },
    "flooding": {
        "%EOL%": 1,
        "%total%": 1
    },
    "surprised": {
        "to": 1,
        "%total%": 1
    },
    "Conservative": {
        "thinkers": 1,
        "%total%": 1
    },
    "thinkers": {
        "like": 1,
        "%total%": 1
    },
    "like": {
        "James": 1,
        "%total%": 1
    },
    "banned": {
        "from": 1,
        "%total%": 2
    },
    "from": {
        "Twitter,": 0.3333333333333333,
        "%total%": 3,
        "Facebook!": 0.6666666666666666,
        "the": 1
    },
    "Twitter,": {
        "and": 1,
        "%total%": 1
    },
    "Paul": {
        "Watson": 1,
        "%total%": 1
    },
    "Watson": {
        "banned": 1,
        "%total%": 1
    },
    "Facebook!": {
        "https://t": 1,
        "%total%": 1
    },
    "co/eHX3Z5CMXb": {
        "The": 1,
        "%total%": 1
    },
    "wonderful": {
        "Diamond": 1,
        "%total%": 1
    },
    "Diamond": {
        "and": 1,
        "%total%": 1
    },
    "Silk": {
        "have": 1,
        "%total%": 1
    },
    "treated": {
        "so": 1,
        "%total%": 1
    },
    "horribly": {
        "by": 1,
        "%total%": 1
    },
    "by": {
        "Facebook": 0.3333333333333333,
        "%total%": 3,
        "bringing": 0.6666666666666666,
        "the": 1
    },
    "work": {
        "so": 0.3333333333333333,
        "%total%": 3,
        "and": 0.6666666666666666,
        "with": 1
    },
    "done": {
        "to": 1,
        "%total%": 1
    },
    "them": {
        "is": 1,
        "%total%": 1
    },
    "sad": {
        "-": 1,
        "%total%": 1
    },
    "we’re": {
        "looking": 1,
        "%total%": 1
    },
    "into": {
        "%EOL%": 0.5,
        "%total%": 2,
        "#2020": 1
    },
    "It’s": {
        "getting": 1,
        "%total%": 1
    },
    "worse": {
        "and": 0.5,
        "%total%": 2,
        "for": 1
    },
    "Conservatives": {
        "on": 1,
        "%total%": 1
    },
    "social": {
        "media!": 0.5,
        "%total%": 2,
        "media": 1
    },
    "media!": {
        "I": 1,
        "%total%": 1
    },
    "continuing": {
        "to": 1,
        "%total%": 1
    },
    "monitor": {
        "the": 1,
        "%total%": 1
    },
    "censorship": {
        "of": 1,
        "%total%": 1
    },
    "AMERICAN": {
        "CITIZENS": 1,
        "%total%": 1
    },
    "CITIZENS": {
        "on": 1,
        "%total%": 1
    },
    "platforms": {
        "%EOL%": 1,
        "%total%": 1
    },
    "United": {
        "States": 1,
        "%total%": 2
    },
    "States": {
        "of": 0.5,
        "%total%": 2,
        "–": 1
    },
    "—": {
        "and": 1,
        "%total%": 2
    },
    "what’s": {
        "known": 1,
        "%total%": 1
    },
    "known": {
        "as": 1,
        "%total%": 1
    },
    "FREEDOM": {
        "OF": 1,
        "%total%": 1
    },
    "OF": {
        "SPEECH!": 0.5,
        "%total%": 2,
        "GOD!": 1
    },
    "SPEECH!": {
        "We": 1,
        "%total%": 1
    },
    "We": {
        "are": 0.4,
        "%total%": 5,
        "discussed": 0.6000000000000001,
        "can": 0.8,
        "give": 1
    },
    "monitoring": {
        "and": 1,
        "%total%": 1
    },
    "watching,": {
        "closely!!": 1,
        "%total%": 1
    },
    "closely!!": {
        "The": 1,
        "%total%": 1
    },
    "International": {
        "Association": 1,
        "%total%": 1
    },
    "Association": {
        "of": 1,
        "%total%": 1
    },
    "Firefighters": {
        "Union": 1,
        "%total%": 1
    },
    "Union": {
        "is": 1,
        "%total%": 1
    },
    "rebelling": {
        "on": 1,
        "%total%": 1
    },
    "their": {
        "very": 0.3333333333333333,
        "%total%": 3,
        "best": 0.6666666666666666,
        "lack": 1
    },
    "foolish": {
        "leader": 1,
        "%total%": 1
    },
    "leader": {
        "%EOL%": 1,
        "%total%": 1
    },
    "vote": {
        "him": 1,
        "%total%": 1
    },
    "out": {
        "of": 1,
        "%total%": 1
    },
    "office": {
        "%EOL%": 1,
        "%total%": 1
    },
    "doesn’t": {
        "get": 1,
        "%total%": 1
    },
    "get": {
        "it!": 0.5,
        "%total%": 2,
        "back": 1
    },
    "it!": {
        "https://t": 1,
        "%total%": 1
    },
    "co/NmaasMxOLE": {
        "https://t": 1,
        "%total%": 1
    },
    "co/7tMG5NtvwO": {
        "RT": 1,
        "%total%": 1
    },
    "welcomed": {
        "Prime": 1,
        "%total%": 1
    },
    "Prime": {
        "Minister": 1,
        "%total%": 1
    },
    "Minister": {
        "Peter": 1,
        "%total%": 1
    },
    "Peter": {
        "Pellegrini": 1,
        "%total%": 1
    },
    "Pellegrini": {
        "of": 1,
        "%total%": 1
    },
    "Slovak": {
        "Republic": 1,
        "%total%": 1
    },
    "Republic": {
        "for": 1,
        "%total%": 1
    },
    "first": {
        "visit": 0.5,
        "%total%": 2,
        "time,": 1
    },
    "visit": {
        "in": 1,
        "%total%": 1
    },
    "Oval": {
        "Office": 1,
        "%total%": 1
    },
    "Office": {
        "toda…": 1,
        "%total%": 1
    },
    "toda…": {
        "Fred": 1,
        "%total%": 1
    },
    "Fred": {
        "Keller": 1,
        "%total%": 1
    },
    "Keller": {
        "of": 1,
        "%total%": 1
    },
    "State": {
        "of": 0.5,
        "%total%": 2,
        "Rep": 1
    },
    "Pennsylvania": {
        "has": 0.5,
        "%total%": 2,
        "and": 1
    },
    "outstanding": {
        "State": 1,
        "%total%": 1
    },
    "Rep": {
        "%EOL%": 1,
        "%total%": 1
    },
    "Now": {
        "he": 1,
        "%total%": 1
    },
    "he": {
        "is": 0.5,
        "%total%": 2,
        "did": 1
    },
    "running": {
        "as": 1,
        "%total%": 1
    },
    "Republican": {
        "Nominee": 1,
        "%total%": 1
    },
    "Nominee": {
        "for": 1,
        "%total%": 1
    },
    "Congress,": {
        "and": 1,
        "%total%": 1
    },
    "my": {
        "Complete": 1,
        "%total%": 1
    },
    "Complete": {
        "and": 1,
        "%total%": 1
    },
    "Total": {
        "Endorsement": 1,
        "%total%": 1
    },
    "Endorsement": {
        "%EOL%": 1,
        "%total%": 1
    },
    "Strong": {
        "on": 1,
        "%total%": 1
    },
    "Crime,": {
        "Second": 1,
        "%total%": 1
    },
    "Second": {
        "Amendment,": 1,
        "%total%": 1
    },
    "Amendment,": {
        "Military,": 1,
        "%total%": 1
    },
    "Military,": {
        "Vets,": 1,
        "%total%": 1
    },
    "Vets,": {
        "and": 1,
        "%total%": 1
    },
    "Healthcare": {
        "%EOL%": 1,
        "%total%": 1
    },
    "fantastic": {
        "job!": 1,
        "%total%": 1
    },
    "job!": {
        "%EOL%": 1,
        "%total%": 1
    },
    "discussed": {
        "Trade,": 1,
        "%total%": 1
    },
    "Trade,": {
        "Venezuela,": 1,
        "%total%": 1
    },
    "Venezuela,": {
        "Ukraine,": 1,
        "%total%": 1
    },
    "Ukraine,": {
        "North": 1,
        "%total%": 1
    },
    "Nuclear": {
        "Arms": 1,
        "%total%": 1
    },
    "Arms": {
        "Control": 1,
        "%total%": 1
    },
    "Control": {
        "and": 1,
        "%total%": 1
    },
    "even": {
        "the": 1,
        "%total%": 1
    },
    "“Russian": {
        "Hoax": 1,
        "%total%": 1
    },
    "Hoax": {
        "%EOL%": 1,
        "%total%": 1
    },
    "productive": {
        "talk!": 1,
        "%total%": 1
    },
    "talk!": {
        "Had": 1,
        "%total%": 1
    },
    "Had": {
        "a": 1,
        "%total%": 1
    },
    "long": {
        "and": 0.5,
        "%total%": 2,
        "before": 1
    },
    "conversation": {
        "with": 1,
        "%total%": 1
    },
    "always": {
        "said,": 1,
        "%total%": 1
    },
    "said,": {
        "long": 1,
        "%total%": 1
    },
    "before": {
        "the": 1,
        "%total%": 1
    },
    "Witch": {
        "Hunt": 1,
        "%total%": 1
    },
    "Hunt": {
        "started,": 1,
        "%total%": 1
    },
    "started,": {
        "getting": 1,
        "%total%": 1
    },
    "along": {
        "with": 1,
        "%total%": 1
    },
    "China,": {
        "and": 1,
        "%total%": 1
    },
    "everyone": {
        "is": 1,
        "%total%": 1
    },
    "thing,": {
        "not": 1,
        "%total%": 1
    },
    "bad": {
        "thing": 0.5,
        "%total%": 2,
        "as": 1
    },
    "agree": {
        "that": 1,
        "%total%": 1
    },
    "AMERICA": {
        "is": 1,
        "%total%": 1
    },
    "now": {
        "#1": 0.5,
        "%total%": 2,
        "Republicans": 1
    },
    "#1": {
        "%EOL%": 1,
        "%total%": 1
    },
    "ENVY": {
        "of": 1,
        "%total%": 1
    },
    "WORLD": {
        "—": 1,
        "%total%": 1
    },
    "yet": {
        "to": 1,
        "%total%": 1
    },
    "come!": {
        "https://t": 1,
        "%total%": 1
    },
    "co/Uc81DzHbu2": {
        "“The": 1,
        "%total%": 1
    },
    "“The": {
        "U": 1,
        "%total%": 1
    },
    "U": {
        "%EOL%": 1,
        "%total%": 1
    },
    "S": {
        "%EOL%": 1,
        "%total%": 1
    },
    "Created": {
        "263,000": 1,
        "%total%": 1
    },
    "263,000": {
        "Jobs": 1,
        "%total%": 1
    },
    "Jobs": {
        "in": 1,
        "%total%": 1
    },
    "April,": {
        "Unemployment": 0.5,
        "%total%": 2,
        "unemployment": 1
    },
    "Unemployment": {
        "Fell": 1,
        "%total%": 1
    },
    "Fell": {
        "to": 1,
        "%total%": 1
    },
    "Lowest": {
        "Level": 1,
        "%total%": 1
    },
    "Level": {
        "Since": 1,
        "%total%": 1
    },
    "Since": {
        "1969”": 1,
        "%total%": 1
    },
    "1969”": {
        "https://t": 1,
        "%total%": 2
    },
    "co/TtQy5yJDku": {
        "JOBS,": 1,
        "%total%": 1
    },
    "JOBS,": {
        "JOBS,": 0.5,
        "%total%": 2,
        "JOBS!": 1
    },
    "JOBS!": {
        "“Jobs": 1,
        "%total%": 1
    },
    "“Jobs": {
        "surge": 1,
        "%total%": 1
    },
    "surge": {
        "in": 1,
        "%total%": 1
    },
    "unemployment": {
        "rate": 1,
        "%total%": 1
    },
    "rate": {
        "falls": 1,
        "%total%": 1
    },
    "falls": {
        "to": 1,
        "%total%": 1
    },
    "lowest": {
        "since": 1,
        "%total%": 1
    },
    "since": {
        "1969”": 1,
        "%total%": 1
    },
    "co/4DGpumMISf": {
        "Finally,": 1,
        "%total%": 1
    },
    "Finally,": {
        "Mainstream": 1,
        "%total%": 1
    },
    "Mainstream": {
        "Media": 1,
        "%total%": 1
    },
    "involved": {
        "-": 1,
        "%total%": 1
    },
    "too": {
        "“hot”": 1,
        "%total%": 1
    },
    "“hot”": {
        "to": 1,
        "%total%": 1
    },
    "avoid": {
        "%EOL%": 1,
        "%total%": 1
    },
    "Pulitzer": {
        "Prize": 1,
        "%total%": 1
    },
    "Prize": {
        "anyone?": 1,
        "%total%": 1
    },
    "anyone?": {
        "The": 1,
        "%total%": 1
    },
    "New": {
        "York": 1,
        "%total%": 1
    },
    "York": {
        "Times,": 1,
        "%total%": 1
    },
    "Times,": {
        "on": 1,
        "%total%": 1
    },
    "front": {
        "page": 1,
        "%total%": 1
    },
    "page": {
        "(finally),": 1,
        "%total%": 1
    },
    "(finally),": {
        "“Details": 1,
        "%total%": 1
    },
    "“Details": {
        "effort": 1,
        "%total%": 1
    },
    "effort": {
        "to": 1,
        "%total%": 1
    },
    "spy": {
        "on": 1,
        "%total%": 1
    },
    "Campaign": {
        "%EOL%": 1,
        "%total%": 1
    },
    "@foxandfriends": {
        "This": 1,
        "%total%": 1
    },
    "bigger": {
        "than": 0.5,
        "%total%": 2,
        "story": 1
    },
    "than": {
        "WATERGATE,": 1,
        "%total%": 1
    },
    "WATERGATE,": {
        "but": 1,
        "%total%": 1
    },
    "reverse!": {
        "RT": 1,
        "%total%": 1
    },
    "@MariaBartiromo:": {
        "\"I": 0.5,
        "%total%": 2,
        "This": 1
    },
    "\"I": {
        "will": 1,
        "%total%": 1
    },
    "declassify": {
        "soon\"": 1,
        "%total%": 1
    },
    "soon\"": {
        "-": 1,
        "%total%": 1
    },
    "@POTUS": {
        "@realDonaldTrump": 1,
        "%total%": 1
    },
    "@FoxNews": {
        "@FoxBusiness": 1,
        "%total%": 1
    },
    "@FoxBusiness": {
        "RT": 1,
        "%total%": 1
    },
    "become": {
        "an": 1,
        "%total%": 1
    },
    "imp": {
        "&amp;": 1,
        "%total%": 1
    },
    "going": {
        "into": 1,
        "%total%": 1
    },
    "#2020": {
        "⁦@GOPLeader⁩": 1,
        "%total%": 1
    },
    "⁦@GOPLeader⁩": {
        "⁦@realDonaldTrump⁩": 1,
        "%total%": 1
    },
    "⁦@realDonaldTrump⁩": {
        "⁦@MorningsMaria⁩": 1,
        "%total%": 1
    },
    "⁦@MorningsMaria⁩": {
        "⁦@FoxBusiness⁩…": 1,
        "%total%": 1
    },
    "⁦@FoxBusiness⁩…": {
        "RT": 1,
        "%total%": 1
    },
    "fixing": {
        "American": 1,
        "%total%": 1
    },
    "American": {
        "trade": 0.5,
        "%total%": 2,
        "people": 1
    },
    "trade": {
        "to": 1,
        "%total%": 1
    },
    "bring": {
        "our": 1,
        "%total%": 1
    },
    "steel": {
        "and": 0.5,
        "%total%": 2,
        "mill": 1
    },
    "manufacturing": {
        "jobs": 1,
        "%total%": 1
    },
    "jobs": {
        "back": 1,
        "%total%": 1
    },
    "back": {
        "HOME!": 0.5,
        "%total%": 2,
        "to": 1
    },
    "HOME!": {
        "https://t": 1,
        "%total%": 1
    },
    "co/PjD6…": {
        "RT": 1,
        "%total%": 1
    },
    "Happy": {
        "National": 1,
        "%total%": 1
    },
    "National": {
        "Space": 1,
        "%total%": 1
    },
    "Space": {
        "Day!": 1,
        "%total%": 1
    },
    "Day!": {
        "🚀": 1,
        "%total%": 1
    },
    "🚀": {
        "America": 1,
        "%total%": 1
    },
    "space,": {
        "and": 1,
        "%total%": 1
    },
    "making": {
        "sure": 1,
        "%total%": 1
    },
    "sure": {
        "no": 1,
        "%total%": 1
    },
    "no": {
        "other": 1,
        "%total%": 1
    },
    "other": {
        "country…": 0.5,
        "%total%": 2,
        "party": 1
    },
    "country…": {
        "%EOL%": 1,
        "%total%": 1
    },
    "every": {
        "turn": 1,
        "%total%": 1
    },
    "turn": {
        "in": 1,
        "%total%": 1
    },
    "attempts": {
        "to": 1,
        "%total%": 1
    },
    "gain": {
        "access": 1,
        "%total%": 1
    },
    "access": {
        "%EOL%": 1,
        "%total%": 1
    },
    "But": {
        "now": 0.5,
        "%total%": 2,
        "he": 1
    },
    "Republicans": {
        "and": 1,
        "%total%": 1
    },
    "Democrats": {
        "must": 1,
        "%total%": 1
    },
    "come": {
        "together": 1,
        "%total%": 1
    },
    "together": {
        "for": 1,
        "%total%": 1
    },
    "No": {
        "more": 0.5,
        "%total%": 2,
        "Collusion": 1
    },
    "more": {
        "costly": 0.3333333333333333,
        "%total%": 3,
        "-": 0.6666666666666666,
        "prosperous/secure": 1
    },
    "costly": {
        "&amp;": 1,
        "%total%": 1
    },
    "consuming": {
        "investigations": 1,
        "%total%": 1
    },
    "investigations": {
        "%EOL%": 1,
        "%total%": 1
    },
    "Lets": {
        "do": 1,
        "%total%": 1
    },
    "Immigration": {
        "(Border),": 1,
        "%total%": 1
    },
    "(Border),": {
        "Infrastructure,": 1,
        "%total%": 1
    },
    "Infrastructure,": {
        "much": 1,
        "%total%": 1
    },
    "much": {
        "lower": 0.5,
        "%total%": 2,
        "more": 1
    },
    "lower": {
        "drug": 1,
        "%total%": 1
    },
    "drug": {
        "prices": 1,
        "%total%": 1
    },
    "prices": {
        "&amp;": 1,
        "%total%": 1
    },
    "now!": {
        "OK,": 1,
        "%total%": 1
    },
    "OK,": {
        "so": 1,
        "%total%": 1
    },
    "after": {
        "two": 1,
        "%total%": 1
    },
    "two": {
        "years": 1,
        "%total%": 1
    },
    "years": {
        "of": 1,
        "%total%": 1
    },
    "each": {
        "party": 1,
        "%total%": 1
    },
    "party": {
        "trying": 0.5,
        "%total%": 2,
        "look": 1
    },
    "trying": {
        "their": 1,
        "%total%": 1
    },
    "make": {
        "the": 0.5,
        "%total%": 2,
        "Pennsylvania": 1
    },
    "look": {
        "as": 1,
        "%total%": 1
    },
    "it’s": {
        "time": 1,
        "%total%": 1
    },
    "business": {
        "%EOL%": 1,
        "%total%": 1
    },
    "Mueller": {
        "Report": 0.5,
        "%total%": 2,
        "not": 1
    },
    "Report": {
        "strongly": 1,
        "%total%": 1
    },
    "strongly": {
        "stated": 1,
        "%total%": 1
    },
    "stated": {
        "that": 1,
        "%total%": 1
    },
    "there": {
        "was": 1,
        "%total%": 1
    },
    "(of": {
        "course)": 1,
        "%total%": 1
    },
    "course)": {
        "and,": 1,
        "%total%": 1
    },
    "and,": {
        "in": 1,
        "%total%": 1
    },
    "fact,": {
        "they": 1,
        "%total%": 1
    },
    "were": {
        "rebuffed": 1,
        "%total%": 1
    },
    "rebuffed": {
        "%EOL%": 1,
        "%total%": 1
    },
    "Thank": {
        "you,": 1,
        "%total%": 1
    },
    "you,": {
        "working": 1,
        "%total%": 1
    },
    "working": {
        "hard!": 0.5,
        "%total%": 2,
        "%EOL%": 1
    },
    "hard!": {
        "#MAGA": 1,
        "%total%": 1
    },
    "#MAGA": {
        "https://t": 1,
        "%total%": 1
    },
    "co/jwsb75t0WW": {
        "Proclamation": 1,
        "%total%": 1
    },
    "Proclamation": {
        "on": 1,
        "%total%": 1
    },
    "Days": {
        "of": 1,
        "%total%": 1
    },
    "Remembrance": {
        "of": 1,
        "%total%": 1
    },
    "Victims": {
        "of": 1,
        "%total%": 1
    },
    "Holocaust:": {
        "https://t": 1,
        "%total%": 1
    },
    "co/l5nVFKI9fr": {
        "https://t": 1,
        "%total%": 1
    },
    "co/vGPOelEesM": {
        "Congrats": 1,
        "%total%": 1
    },
    "Congrats": {
        "to": 1,
        "%total%": 1
    },
    "@U_S_Steel": {
        "for": 1,
        "%total%": 1
    },
    "investing": {
        "$1+": 1,
        "%total%": 1
    },
    "$1+": {
        "BILLION": 1,
        "%total%": 1
    },
    "BILLION": {
        "in": 1,
        "%total%": 1
    },
    "America's": {
        "most": 1,
        "%total%": 1
    },
    "most": {
        "INNOVATIVE": 1,
        "%total%": 1
    },
    "INNOVATIVE": {
        "steel": 1,
        "%total%": 1
    },
    "mill": {
        "%EOL%": 1,
        "%total%": 1
    },
    "Tariffs": {
        "make": 0.5,
        "%total%": 2,
        "are": 1
    },
    "prosperous/secure": {
        "by": 1,
        "%total%": 1
    },
    "bringing": {
        "Steel": 1,
        "%total%": 1
    },
    "Steel": {
        "and": 0.5,
        "%total%": 2,
        "City": 1
    },
    "Aluminum": {
        "industries": 1,
        "%total%": 1
    },
    "industries": {
        "BACK": 1,
        "%total%": 1
    },
    "BACK": {
        "%EOL%": 1,
        "%total%": 1
    },
    "Pittsburgh": {
        "is": 1,
        "%total%": 1
    },
    "again": {
        "The": 0.5,
        "%total%": 2,
        "place": 1
    },
    "City": {
        "%EOL%": 1,
        "%total%": 1
    },
    "Economy": {
        "is": 1,
        "%total%": 1
    },
    "BOOMING!": {
        "https://t": 1,
        "%total%": 1
    },
    "co/XPXjxli6uc": {
        "On": 1,
        "%total%": 1
    },
    "On": {
        "this": 1,
        "%total%": 1
    },
    "day": {
        "of": 1,
        "%total%": 2
    },
    "prayer,": {
        "we": 1,
        "%total%": 2
    },
    "once": {
        "again": 1,
        "%total%": 1
    },
    "hopes": {
        "in": 1,
        "%total%": 1
    },
    "hands": {
        "of": 1,
        "%total%": 1
    },
    "Creator": {
        "%EOL%": 1,
        "%total%": 1
    },
    "give": {
        "thanks": 1,
        "%total%": 1
    },
    "thanks": {
        "for": 1,
        "%total%": 1
    },
    "wondrous": {
        "land": 1,
        "%total%": 1
    },
    "land": {
        "of": 1,
        "%total%": 1
    },
    "liberty,": {
        "&amp;": 1,
        "%total%": 1
    },
    "pray": {
        "that": 0.5,
        "%total%": 2,
        "and": 1
    },
    "THIS": {
        "nation": 1,
        "%total%": 1
    },
    "nation": {
        "–": 1,
        "%total%": 1
    },
    "–": {
        "OUR": 0.25,
        "%total%": 4,
        "these": 0.5,
        "will": 0.75,
        "and": 1
    },
    "OUR": {
        "home": 1,
        "%total%": 1
    },
    "home": {
        "–": 1,
        "%total%": 1
    },
    "these": {
        "United": 1,
        "%total%": 1
    },
    "forever": {
        "be": 1,
        "%total%": 1
    },
    "strengthened": {
        "by": 1,
        "%total%": 1
    },
    "Goodness": {
        "and": 1,
        "%total%": 1
    },
    "Grace": {
        "&amp;": 1,
        "%total%": 1
    },
    "eternal": {
        "GLORY": 1,
        "%total%": 1
    },
    "GLORY": {
        "OF": 1,
        "%total%": 1
    },
    "GOD!": {
        "https://t": 1,
        "%total%": 1
    },
    "co/RtSI3j1GWH": {
        "As": 1,
        "%total%": 1
    },
    "unite": {
        "on": 1,
        "%total%": 1
    },
    "renew": {
        "our": 1,
        "%total%": 1
    },
    "resolve": {
        "to": 1,
        "%total%": 1
    },
    "protect": {
        "communities": 1,
        "%total%": 1
    },
    "communities": {
        "of": 1,
        "%total%": 1
    },
    "faith": {
        "–": 1,
        "%total%": 1
    },
    "ensure": {
        "that": 1,
        "%total%": 1
    },
    "ALL": {
        "of": 1,
        "%total%": 1
    },
    "live,": {
        "pray": 1,
        "%total%": 1
    },
    "worship": {
        "IN": 1,
        "%total%": 1
    },
    "IN": {
        "PEACE": 1,
        "%total%": 1
    },
    "PEACE": {
        "%EOL%": 1,
        "%total%": 1
    },
    "#NationalDayOfPrayer": {
        "https://t": 1,
        "%total%": 1
    },
    "co/1a7zphaE6z": {
        "%EOL%": 1,
        "%total%": 1
    },
    "deregulation": {
        "which": 1,
        "%total%": 1
    },
    "produced": {
        "non-inflationary": 1,
        "%total%": 1
    },
    "non-inflationary": {
        "prosperity": 1,
        "%total%": 1
    },
    "prosperity": {
        "for": 1,
        "%total%": 1
    },
    "Americans": {
        "%EOL%": 1,
        "%total%": 1
    },
    "I’ve": {
        "asked": 1,
        "%total%": 1
    },
    "asked": {
        "Steve": 1,
        "%total%": 1
    },
    "Steve": {
        "to": 0.3333333333333333,
        "%total%": 3,
        "Moore,": 0.6666666666666666,
        "won": 1
    },
    "toward": {
        "future": 1,
        "%total%": 1
    },
    "future": {
        "economic": 1,
        "%total%": 1
    },
    "growth": {
        "in": 1,
        "%total%": 1
    },
    "Moore,": {
        "a": 1,
        "%total%": 1
    },
    "pro-growth": {
        "economist": 1,
        "%total%": 1
    },
    "economist": {
        "and": 1,
        "%total%": 1
    },
    "fine": {
        "person,": 1,
        "%total%": 1
    },
    "person,": {
        "has": 1,
        "%total%": 1
    },
    "decided": {
        "to": 1,
        "%total%": 1
    },
    "withdraw": {
        "from": 1,
        "%total%": 1
    },
    "Fed": {
        "process": 1,
        "%total%": 1
    },
    "process": {
        "%EOL%": 1,
        "%total%": 1
    },
    "won": {
        "the": 1,
        "%total%": 1
    },
    "battle": {
        "of": 1,
        "%total%": 1
    },
    "ideas": {
        "including": 1,
        "%total%": 1
    },
    "including": {
        "Tax": 1,
        "%total%": 1
    },
    "Tax": {
        "Cuts": 1,
        "%total%": 1
    },
    "Cuts": {
        "%EOL%": 1,
        "%total%": 1
    },
    "@ByronYork:": {
        "I": 1,
        "%total%": 1
    },
    "talk": {
        "about": 1,
        "%total%": 1
    },
    "deciding": {
        "on": 1,
        "%total%": 1
    },
    "obstruction": {
        "%EOL%": 1,
        "%total%": 1
    },
    "didn't": {
        "he?": 1,
        "%total%": 1
    },
    "he?": {
        "If": 1,
        "%total%": 1
    },
    "If": {
        "you're": 1,
        "%total%": 1
    },
    "you're": {
        "investigated…": 1,
        "%total%": 1
    },
    "investigated…": {
        "RT": 1,
        "%total%": 1
    },
    "@kenvogel:": {
        "NEW:": 1,
        "%total%": 1
    },
    "NEW:": {
        "The": 1,
        "%total%": 1
    },
    "BIDENS": {
        "are": 1,
        "%total%": 1
    },
    "entangled": {
        "in": 1,
        "%total%": 1
    },
    "Ukrainian": {
        "corruption": 1,
        "%total%": 1
    },
    "corruption": {
        "scandal:": 1,
        "%total%": 1
    },
    "scandal:": {
        "@JoeBiden": 1,
        "%total%": 1
    },
    "@JoeBiden": {
        "pushed": 1,
        "%total%": 1
    },
    "pushed": {
        "Ukraine": 1,
        "%total%": 1
    },
    "Ukraine": {
        "to": 1,
        "%total%": 1
    },
    "fire": {
        "a": 1,
        "%total%": 1
    },
    "prosecutor": {
        "seen": 1,
        "%total%": 1
    },
    "seen": {
        "as": 1,
        "%total%": 1
    },
    "corrup…": {
        "RT": 1,
        "%total%": 1
    },
    "@RichLowry:": {
        "NR’s": 1,
        "%total%": 1
    },
    "NR’s": {
        "editorial:": 1,
        "%total%": 1
    },
    "editorial:": {
        "“Not": 1,
        "%total%": 1
    },
    "“Not": {
        "for": 1,
        "%total%": 1
    },
    "time,": {
        "or": 1,
        "%total%": 1
    },
    "expect,": {
        "the": 1,
        "%total%": 1
    },
    "last,": {
        "Bill": 1,
        "%total%": 1
    },
    "Bill": {
        "Barr’s": 1,
        "%total%": 1
    },
    "Barr’s": {
        "critics": 1,
        "%total%": 1
    },
    "critics": {
        "are": 1,
        "%total%": 1
    },
    "demonstrating": {
        "their": 1,
        "%total%": 1
    },
    "lack": {
        "of": 1,
        "%total%": 1
    },
    "judgme…": {
        "%EOL%": 1,
        "%total%": 1
    }
}